_nx_arangodb/VERSION
_nx_arangodb/__init__.py
_nx_arangodb/_version.py
_nx_arangodb/core.py
nx_arangodb/__init__.py
nx_arangodb/convert.py
nx_arangodb/exceptions.py
nx_arangodb/interface.py
nx_arangodb/logger.py
nx_arangodb/typing.py
nx_arangodb/algorithms/__init__.py
nx_arangodb/algorithms/shortest_paths/__init__.py
nx_arangodb/algorithms/shortest_paths/generic.py
nx_arangodb/classes/__init__.py
nx_arangodb/classes/coreviews.py
nx_arangodb/classes/digraph.py
nx_arangodb/classes/enum.py
nx_arangodb/classes/function.py
nx_arangodb/classes/graph.py
nx_arangodb/classes/multidigraph.py
nx_arangodb/classes/multigraph.py
nx_arangodb/classes/reportviews.py
nx_arangodb/classes/dict/__init__.py
nx_arangodb/classes/dict/adj.py
nx_arangodb/classes/dict/graph.py
nx_arangodb/classes/dict/node.py
nx_arangodb/utils/__init__.py
nx_arangodb/utils/decorators.py
nx_arangodb/utils/misc.py
nx_arangodb-1.3.1.dist-info/licenses/LICENSE
nx_arangodb-1.3.1.dist-info/METADATA
nx_arangodb-1.3.1.dist-info/WHEEL
nx_arangodb-1.3.1.dist-info/entry_points.txt
nx_arangodb-1.3.1.dist-info/top_level.txt
nx_arangodb-1.3.1.dist-info/RECORD
