Metadata-Version: 2.4
Name: nx-arangodb
Version: 1.3.1
Summary: ArangoDB backend for NetworkX
Author: ArangoDB
License: Apache 2.0
Project-URL: Homepage, https://github.com/arangodb/nx-arangodb
Classifier: License :: OSI Approved :: Apache Software License
Classifier: Programming Language :: Python
Classifier: Programming Language :: Python :: 3
Classifier: Programming Language :: Python :: 3.10
Classifier: Programming Language :: Python :: 3.11
Classifier: Programming Language :: Python :: 3.12
Classifier: Programming Language :: Python :: 3.13
Classifier: Programming Language :: Python :: 3 :: Only
Classifier: Intended Audience :: Developers
Classifier: Topic :: Software Development :: Libraries :: Python Modules
Requires-Python: <3.14,>=3.10
License-File: LICENSE
Requires-Dist: networkx<=3.5,>=3.0
Requires-Dist: phenolrs==0.5.10
Requires-Dist: python-arango~=8.1
Requires-Dist: adbnx-adapter~=5.0
Provides-Extra: dev
Requires-Dist: packaging>=21; extra == "dev"
Requires-Dist: pandas; extra == "dev"
Requires-Dist: pytest; extra == "dev"
Requires-Dist: pytest-benchmark; extra == "dev"
Requires-Dist: pytest-cov; extra == "dev"
Requires-Dist: pytest-mpl; extra == "dev"
Requires-Dist: pytest-xdist; extra == "dev"
Requires-Dist: scipy; extra == "dev"
Requires-Dist: black; extra == "dev"
Requires-Dist: flake8; extra == "dev"
Requires-Dist: Flake8-pyproject; extra == "dev"
Requires-Dist: isort; extra == "dev"
Requires-Dist: mypy; extra == "dev"
Requires-Dist: pandas; extra == "dev"
Requires-Dist: sphinx; extra == "dev"
Requires-Dist: sphinx_rtd_theme; extra == "dev"
Provides-Extra: llm
Requires-Dist: langchain-arangodb; extra == "llm"
Requires-Dist: langchain_openai; extra == "llm"
Dynamic: license-file
